life_web_ui/__init__.py
life_web_ui/web/static/Icon.png
life_web_ui/web/static/life-web.js
life_web_ui/web/t/home.html
life_web_ui-0.1.0.1.dist-info/METADATA
life_web_ui-0.1.0.1.dist-info/WHEEL
life_web_ui-0.1.0.1.dist-info/entry_points.txt
life_web_ui-0.1.0.1.dist-info/top_level.txt
life_web_ui-0.1.0.1.dist-info/RECORD
