Metadata-Version: 2.1
Name: life-web-ui
Version: 0.1.0.1
Summary: Web-based UI for Conway Game of Life
Home-page: https://github.com/kign/life/tree/master/py-web
Author: Konstantin Ignatiev
Author-email: kostya@inet-lab.net
License: UNKNOWN
Project-URL: Bug Tracker, https://github.com/kign/life/issues
Platform: UNKNOWN
Classifier: Programming Language :: Python :: 3
Classifier: License :: OSI Approved :: GNU General Public License v2 (GPLv2)
Classifier: Operating System :: OS Independent
Requires-Python: >=3.7
Requires-Dist: flask
Requires-Dist: inetlab
Requires-Dist: conway-life (>=0.1.4)
